power_strip/__init__.py
power_strip/v1alpha1/__init__.py
power_strip/v1alpha1/api_pb2.py
power_strip/v1alpha1/api_pb2_grpc.py
power_strip-0.1.4.dist-info/WHEEL
power_strip-0.1.4.dist-info/METADATA
power_strip-0.1.4.dist-info/RECORD
